audio/__init__.py
graphics/__init__.py
graphics/character/__init__.py
graphics/enemy/__init__.py
pyPlatFinal-0.0.1.dist-info/METADATA
pyPlatFinal-0.0.1.dist-info/WHEEL
pyPlatFinal-0.0.1.dist-info/top_level.txt
pyPlatFinal-0.0.1.dist-info/RECORD
