Metadata-Version: 2.1
Name: pyPlatFinal
Version: 0.0.1
Summary: Python Pygame Final Project
Author: Dylan Watson and Milo Moore
Author-email: <jwatson8@g.emporia.edu>
Keywords: python,simpleCalpackage
Classifier: Development Status :: 3 - Alpha
Classifier: Intended Audience :: Education
Classifier: Programming Language :: Python :: 2
Classifier: Programming Language :: Python :: 3
Classifier: Operating System :: MacOS :: MacOS X
Classifier: Operating System :: Microsoft :: Windows
Requires-Dist: pygame
